treediskrings/__init__.py
treediskrings/analysis/__init__.py
treediskrings/analysis/chain_analysis_tools.py
treediskrings/analysis/chain_neighbourhood.py
treediskrings/analysis/chain_system_manager.py
treediskrings/analysis/chains_bag.py
treediskrings/analysis/connect_chains.py
treediskrings/analysis/connect_parameters.py
treediskrings/analysis/interpolation_nodes.py
treediskrings/analyzer.py
treediskrings/cli.py
treediskrings/config.py
treediskrings/detection/__init__.py
treediskrings/detection/canny_devernay_edge_detector.py
treediskrings/detection/filter_edges.py
treediskrings/externals/__init__.py
treediskrings/externals/linux-arm/__init__.py
treediskrings/externals/linux-arm/devernay.out
treediskrings/externals/linux-x86_64/__init__.py
treediskrings/externals/linux-x86_64/devernay.out
treediskrings/externals/macos-arm64/__init__.py
treediskrings/externals/macos-arm64/devernay.out
treediskrings/geometry/__init__.py
treediskrings/geometry/angular_set.py
treediskrings/geometry/chain.py
treediskrings/geometry/curve.py
treediskrings/geometry/geometry_utils.py
treediskrings/geometry/node.py
treediskrings/geometry/ray.py
treediskrings/geometry/ring.py
treediskrings/geometry/virtual_band_generator.py
treediskrings/main.py
treediskrings/processing/__init__.py
treediskrings/processing/chain_context.py
treediskrings/processing/postprocessing.py
treediskrings/processing/preprocessing.py
treediskrings/processing/sampling.py
treediskrings/utils/__init__.py
treediskrings/utils/file_utils.py
treediskrings/utils/results_handler.py
treediskrings/visualization/__init__.py
treediskrings/visualization/color.py
treediskrings/visualization/drawing.py
tree_disk_rings-0.6.1.dist-info/METADATA
tree_disk_rings-0.6.1.dist-info/WHEEL
tree_disk_rings-0.6.1.dist-info/entry_points.txt
tree_disk_rings-0.6.1.dist-info/RECORD
