Metadata-Version: 2.3
Name: tree-disk-rings
Version: 0.6.1
Summary: A package for tree disk rings detection in images
License: MIT
Keywords: tree,rings,image processing
Author: Tony
Author-email: tonymeissner70@gmail.com
Requires-Python: >=3.10
Classifier: License :: OSI Approved :: MIT License
Classifier: Programming Language :: Python :: 3
Classifier: Programming Language :: Python :: 3.10
Classifier: Programming Language :: Python :: 3.11
Classifier: Programming Language :: Python :: 3.12
Classifier: Programming Language :: Python :: 3.13
Requires-Dist: glob2 (>=0.7,<0.8)
Requires-Dist: imageio (>=2.36.0,<3.0.0)
Requires-Dist: matplotlib (>=3.9.2,<4.0.0)
Requires-Dist: natsort (>=8.4.0,<9.0.0)
Requires-Dist: numpy (>=1.23.0,<2.0.0)
Requires-Dist: opencv-contrib-python-headless (>=4.10.0.84,<5.0.0.0)
Requires-Dist: opencv-python (>=4.11.0.86,<5.0.0.0)
Requires-Dist: opencv-python-headless (>=4.11.0.86,<5.0.0.0)
Requires-Dist: pandas (>=2.2.3,<3.0.0)
Requires-Dist: pillow (>=11.0.0,<12.0.0)
Requires-Dist: scikit-image (>=0.24.0,<0.25.0)
Requires-Dist: scikit-learn (>=1.5.2,<2.0.0)
Requires-Dist: shapely (>=2.0.6,<3.0.0)
Requires-Dist: torch (>=2.5.1,<3.0.0)
Requires-Dist: torchvision (>=0.20.1,<0.21.0)
Project-URL: Homepage, https://github.com/tuke307/tree-disk-analyzer
Project-URL: Repository, https://github.com/tuke307/tree-disk-analyzer
